{
  "Blackout Blinds": 99,
  "Chairs with Tables": 197,
  "Computer Equipment": 226,
  "DVD VHS Player": 60,
  "Data Projector XGA": 120,
  "Managed PC": 162,
  "Microphone, Lapel": 40,
  "OHP": 52,
  "Projection Screen": 133,
  "Telephone": 157,
  "White Board": 235,
  "DVD Player": 61,
  "Visualiser": 92,
  "Blackboard": 4,
  "Fixed Seating": 44,
  "Slide Projector": 7,
  "Audio MIxer DSP": 3,
  "Data Projector HD": 4,
  "Induction Loop": 17,
  "Induction Loop Amp": 23,
  "LectureCast": 46,
  "Microphone, Lectern": 2,
  "PA Amplifier": 2,
  "Seating with Tablets": 14,
  "Sympodium": 4,
  "Video Conference": 1,
  "Microphone, Lapel, Radio": 23,
  "Microphone Conference": 3,
  "Microphone, Bench, Radio": 7,
  "Avoid Dual Projection": 21,
  "Plasma screen": 34,
  "X-Ray Light Box": 3,
  "Computer Link": 4,
  "Audio Amplifier": 82,
  "Flipchart": 29,
  "Room Control": 27,
  "VHS Recorder/Player": 5,
  "Loudspeaker, Low Impedance": 24,
  "Video Camera": 4,
  "Microphone, Bench": 7,
  "Miscellaneous": 5,
  "Audio Mixers": 10,
  "Radio Mic Receiver": 6,
  "Screen": 6,
  "Wheelchair accessible": 35,
  "Blu Ray Player": 5,
  "Loudspeaker/Amplifier": 2,
  "Software - 7Zip": 9,
  "Software - AMASeis": 9,
  "Software - Acrobat Reader": 9,
  "Software - Adlib archive": 9,
  "Software - Antioch": 9,
  "Software - AquaChem": 9,
  "Software - Aquifer Test": 9,
  "Software - ArcGIS": 9,
  "Software - Atlas.ti": 9,
  "Software - Audacity": 9,
  "Software - C2": 9,
  "Software - Cano Draw": 9,
  "Software - Canoco": 9,
  "Software - ChemSketch": 9,
  "Software - CrimeStat": 9,
  "Software - DemoGraphics": 9,
  "Software - DepthMap": 9,
  "Software - DjVu plugin": 9,
  "Software - Dreamweaver": 9,
  "Software - Eclipse": 9,
  "Software - Elib": 9,
  "Software - Embryonic Disk": 9,
  "Software - Endnote": 9,
  "Software - Envi": 1,
  "Software - Epidata": 9,
  "Software - EstimateS": 9,
  "Software - Firefox": 9,
  "Software - Flash": 9,
  "Software - Flowpath II": 9,
  "Software - GAMS": 9,
  "Software - GRASS": 9,
  "Software - GW Contour": 9,
  "Software - GeoDa": 9,
  "Software - GeoModel": 9,
  "Software - GeoTrig": 9,
  "Software - Ghostscript/GSView": 9,
  "Software - Google Earth": 9,
  "Software - Google Sketch Up": 9,
  "Software - Hot Potatoes": 9,
  "Software - IHMC Cmap Tools": 9,
  "Software - ISIS/Draw": 9,
  "Software - Illustrator": 9,
  "Software - In Design": 9,
  "Software - Internet Explorer": 9,
  "Software - Irfanview": 9,
  "Software - JDK": 9,
  "Software - LAPT": 9,
  "Software - Labview": 9,
  "Software - Lisrel": 9,
  "Software - MLWin": 9,
  "Software - MS Project": 9,
  "Software - Mathematica": 9,
  "Software - Matlab": 9,
  "Software - Mesquite": 9,
  "Software - Minitab": 9,
  "Software - Moodle": 9,
  "Software - Movie Maker": 9,
  "Software - Neuron": 9,
  "Software - Notepad ++": 9,
  "Software - Nvivo": 9,
  "Software - Office 2003": 9,
  "Software - Open Office": 9,
  "Software - OxCal": 9,
  "Software - PAST": 9,
  "Software - PDF Converter": 9,
  "Software - PLAS": 9,
  "Software - Palisade": 9,
  "Software - Pharmacology": 9,
  "Software - Photoshop": 9,
  "Software - Publish Web Pages": 9,
  "Software - Publisher": 9,
  "Software - Putty - SSH client": 9,
  "Software - Pymol": 9,
  "Software - Quicktime Player": 9,
  "Software - R": 9,
  "Software - RasMol": 9,
  "Software - RealPlayer": 9,
  "Software - Reference Manager": 9,
  "Software - SPSS": 9,
  "Software - Seismic Eruption": 9,
  "Software - Seismic Waves": 9,
  "Software - Shockwave Player": 9,
  "Software - Sigma Plot": 9,
  "Software - Speech Filing System": 9,
  "Software - Stata": 9,
  "Software - Stella": 9,
  "Software - Surfer": 9,
  "Software - Switch": 9,
  "Software - T drive utility": 9,
  "Software - Tex/LaTex": 9,
  "Software - Tgview": 9,
  "Software - Thunderbird": 9,
  "Software - Turning Point": 9,
  "Software - Twinspan": 9,
  "Software - VLC": 9,
  "Software - Visio": 9,
  "Software - Visual Basic": 9,
  "Software - Visual PEST": 9,
  "Software - WinBUGS": 9,
  "Software - WinKyst": 9,
  "Software - WinSCP": 9,
  "Software - WinTWINS": 9,
  "Software - Windows Media Player": 9,
  "IS Desktop PCs": 9,
  "IS Cluster Room - Double up on machines": 5,
  "Software - BioC": 8,
  "Software - BioPerl": 8,
  "Software - CVFIT": 8,
  "Software - Cogtool": 8,
  "Software - Digital Shoreline Analysis": 8,
  "Software - Earth Sciences - self learning": 8,
  "Software - Risk": 8,
  "Hard Floor": 5,
  "Electronic voting available": 3,
  "Heat Detection (Not Smoke)": 1,
  "HDD Audio Recorder": 2,
  "Audio Cassette Rec": 2,
  "Slide Accessories (Proj.)": 1,
  "IS Cluster Room - Number of PC's Required": 1
}